inventing_machine/__init__.py
inventing_machine/githf.py
inventing_machine/machina.yaml
inventing_machine-0.0.1.dist-info/LICENSE
inventing_machine-0.0.1.dist-info/METADATA
inventing_machine-0.0.1.dist-info/WHEEL
inventing_machine-0.0.1.dist-info/top_level.txt
inventing_machine-0.0.1.dist-info/RECORD
